signed_pickle/__init__.py
signed_pickle/dumper_signer.py
signed_pickle/pickle_signer.py
signed_pickle/py.typed
signed_pickle-1.0.1.dist-info/LICENSE
signed_pickle-1.0.1.dist-info/WHEEL
signed_pickle-1.0.1.dist-info/METADATA
signed_pickle-1.0.1.dist-info/RECORD
